<?xml version="1.0" encoding="UTF-8"?>
<Dictionary>
  <Item>
    <Key>CVSPLM_Login_Started</Key>
    <Val>Login started ...</Val>
  </Item>
  <Item>
    <Key>CVSPLM_Login</Key>
    <Val>Command Login CVS PLM OK</Val>
  </Item>
  <Item>
    <Key>CVSPLM_Logout</Key>
    <Val>Command Logout OK</Val>
  </Item>
  <Item>
    <Key>CheckOutMessage</Key>
    <Val>Command Check Out OK</Val>
  </Item>
  <Item>
    <Key>CheckInMessage</Key>
    <Val>Command Check In OK</Val>
  </Item>
  <Item>
    <Key>Submit</Key>
    <Val>Command Submit OK</Val>
  </Item>
  <Item>
    <Key>EngDocCreated</Key>
    <Val>Command Create Engineering Doc. OK</Val>
  </Item>
  <Item>
    <Key>CommandShowRelationBrowserOK</Key>
    <Val>Command Show relation browser OK</Val>
  </Item>
  <Item>
    <Key>CommandUpdateOK</Key>
    <Val>Command Update OK</Val>
  </Item>
  <Item>
    <Key>CheckCompletenessFailed</Key>
    <Val>Check Completeness for the item failed. Please correct the errors first.</Val>
  </Item>
  <Item>
    <Key>CommandGetSelectionListOK</Key>
    <Val>Command Get selection list OK</Val>
  </Item>
  <Item>
    <Key>CommandCheckCompletenessOK</Key>
    <Val>Command Check Completeness OK</Val>
  </Item>
  <Item>
    <Key>CommandExpandRelationOK</Key>
    <Val>Command Expand Relation OK</Val>
  </Item>
  <Item>
    <Key>CommandAddDataSheetWasLaunched</Key>
    <Val>Command Add Data Sheet was launched ...</Val>
  </Item>
  <Item>
    <Key>CreateDocumentRequestOK</Key>
    <Val>Command Create Document Request OK</Val>
  </Item> 
  <Item>
    <Key>CommandCreateSalesDocumentOK</Key>
    <Val>Command Create Sales Document OK</Val>
  </Item>
  <Item>
    <Key>FoundItems</Key>
    <Val>^Found.*</Val>
  </Item> 
</Dictionary>
